{"type": "TeamState", "version": "1.0.0", "agent_states": {"group_chat_manager/d97a4206-87a6-4539-820e-115bb0f17fb0": {"type": "RoundRobinManagerState", "version": "1.0.0", "message_thread": [{"source": "user", "models_usage": null, "content": "\n    1. Parse data from the following JSON file: {'Course_Proposal_Form': {'null': ['Title: Certified Kubernetes Application Developer (CKAD) Training', 'Organization: Tertiary Infotech Pte Ltd', 'Learning Outcomes:', 'LO1: Establish high-level structures and frameworks for Kubernetes solutions using appropriate processes and tools.', 'LO2: Align technical, functional, and service requirements within Kubernetes-based solution architectures.', 'LO3: Coordinate multiple Kubernetes solution components to ensure compatibility and meet design framework goals.', 'LO4: Articulate the value of Kubernetes solutions by addressing coding standards, scalability, and reusability.', 'LO5: Establish monitoring and testing processes to validate Kubernetes architectures against business requirements.', 'Couse Duration: 4 days (32 hrs)', 'Instructional Methods:', 'Classroom (15 hrs),', 'Didactic Questioning', 'Demonstration', 'Practice (15 hrs)', 'Assessment Methods:', 'Written Assessment (1 hr)', 'Practical Performance (1 hr)', 'TSC Mapping:', 'TSC Title: Solution Architecture', 'TSC Code: ICT-DES-5006-1.1', 'TSC Knowledge:', 'K1 Process for refining solution architecture', 'K2 Applications of tools and modelling techniques for creation of solution architecture', 'K3 Technical, functional and service considerations', 'K4 Considerations for multiple aspects of the overall solution including performance, security, latency and other relevant aspect for the solution', 'K5 Standards for coding, scalability, integration and reusability', 'K6 Compatibility among multiple solution architecture components and design activities', \"K7 Techniques to measure a solution's value-add\", 'TSC Abilities:', 'A1 Establish high level structures and frameworks to guide the development of IT solutions incorporating various processes, hardware and software components', 'A2 Determine relevant design tools or modelling techniques required to develop a solution architecture and blueprint', 'A3 Align requirements of various internal and external stakeholders, as well as technical, functional and service requirements within a solution architecture', 'A4 Coordinate multiple solution architecture components and design activities, ensuring consistency and compatibility within a target framework', 'A5 Articulate value added by the solution to the business needs', 'A6 Establish processes to regularly monitor, test and review solution architecture against business requirements', 'Learning Units', 'Topic 1: Application Design and Build (K1, K2, A1, A2)', 'Define, build and modify container images', 'Choose and use the right workload resource (Deployment, DaemonSet, CronJob, etc.)', 'Understand multi-container Pod design patterns (e.g. sidecar, init and others)', 'Utilize persistent and ephemeral volumes', 'Topic 2: Application Deployment (K3, A3)', 'Use Kubernetes primitives to implement common deployment strategies (e.g. blue/green or canary)', 'Understand Deployments and how to perform rolling updates', 'Use the Helm package manager to deploy existing packages', 'Kustomize', 'Topic 3: Application Observability and Maintenance (K4, K6, A4)', 'Understand API deprecations', 'Implement probes and health checks', 'Use built-in CLI tools to monitor Kubernetes applications', 'Utilize container logs', 'Debugging in Kubernetes', 'Topic 4: Application Environment, Configuration and Security (K5, A5)', 'Discover and use resources that extend Kubernetes (CRD, Operators)', 'Understand authentication, authorization and admission control', 'Understand requests, limits, quotas', 'Understand ConfigMaps', 'Define resource requirements', 'Create & consume Secrets', 'Understand ServiceAccounts', 'Understand Application Security (SecurityContexts, Capabilities, etc.)', 'Topic 5: Services and Networking (K7, A6)', 'Demonstrate basic understanding of NetworkPolicies', 'Provide and troubleshoot access to applications via services', 'Use Ingress rules to expose applications']}}\n    2. Fix spelling errors, and missing LUs if any.\n    3. Ensure that the LUs do not have the same name as the Topics.\n    4. Return a full JSON object with all the extracted data according to the schema.\n    ", "type": "TextMessage"}, {"source": "tsc_agent", "models_usage": {"prompt_tokens": 2477, "completion_tokens": 1050}, "content": "```json\n{\n    \"Course_Proposal_Form\": {\n        \"null\": [\n            \"Title: Certified Kubernetes Application Developer (CKAD) Training\",\n            \"Organization: Tertiary Infotech Pte Ltd\",\n            \"Learning Outcomes:\",\n            \"LO1: Establish high-level structures and frameworks for Kubernetes solutions using appropriate processes and tools.\",\n            \"LO2: Align technical, functional, and service requirements within Kubernetes-based solution architectures.\",\n            \"LO3: Coordinate multiple Kubernetes solution components to ensure compatibility and meet design framework goals.\",\n            \"LO4: Articulate the value of Kubernetes solutions by addressing coding standards, scalability, and reusability.\",\n            \"LO5: Establish monitoring and testing processes to validate Kubernetes architectures against business requirements.\",\n            \"Course Duration: 4 days (32 hrs)\",\n            \"Instructional Methods:\",\n            \"Classroom (15 hrs),\",\n            \"Didactic Questioning\",\n            \"Demonstration\",\n            \"Practical (15 hrs)\",\n            \"Assessment Methods:\",\n            \"Written Assessment (1 hr)\",\n            \"Practical Performance (1 hr)\",\n            \"TSC Mapping:\",\n            \"TSC Title: Solution Architecture\",\n            \"TSC Code: ICT-DES-5006-1.1\",\n            \"TSC Knowledge:\",\n            \"K1: Process for refining solution architecture\",\n            \"K2: Applications of tools and modelling techniques for creation of solution architecture\",\n            \"K3: Technical, functional and service considerations\",\n            \"K4: Considerations for multiple aspects of the overall solution including performance, security, latency and other relevant aspect for the solution\",\n            \"K5: Standards for coding, scalability, integration and reusability\",\n            \"K6: Compatibility among multiple solution architecture components and design activities\",\n            \"K7: Techniques to measure a solution's value-add\",\n            \"TSC Abilities:\",\n            \"A1: Establish high level structures and frameworks to guide the development of IT solutions incorporating various processes, hardware and software components\",\n            \"A2: Determine relevant design tools or modelling techniques required to develop a solution architecture and blueprint\",\n            \"A3: Align requirements of various internal and external stakeholders, as well as technical, functional and service requirements within a solution architecture\",\n            \"A4: Coordinate multiple solution architecture components and design activities, ensuring consistency and compatibility within a target framework\",\n            \"A5: Articulate value added by the solution to the business needs\",\n            \"A6: Establish processes to regularly monitor, test and review solution architecture against business requirements\",\n            \"Learning Units\"\n        ],\n        \"LU1: Container Image Management (K1, K2, A1, A2)\": [\n            \"Topic 1: Application Design and Build (K1, K2, A1, A2)\",\n            \"Define, build and modify container images\",\n            \"Choose and use the right workload resource (Deployment, DaemonSet, CronJob, etc.)\",\n            \"Understand multi-container Pod design patterns (e.g. sidecar, init and others)\",\n            \"Utilize persistent and ephemeral volumes\"\n        ],\n        \"LU2: Deployment Strategy Implementation (K3, A3)\": [\n            \"Topic 2: Application Deployment (K3, A3)\",\n            \"Use Kubernetes primitives to implement common deployment strategies (e.g. blue/green or canary)\",\n            \"Understand Deployments and how to perform rolling updates\",\n            \"Use the Helm package manager to deploy existing packages\",\n            \"Kustomize\"\n        ],\n        \"LU3: Kubernetes Application Monitoring (K4, K6, A4)\": [\n            \"Topic 3: Application Observability and Maintenance (K4, K6, A4)\",\n            \"Understand API deprecations\",\n            \"Implement probes and health checks\",\n            \"Use built-in CLI tools to monitor Kubernetes applications\",\n            \"Utilize container logs\",\n            \"Debugging in Kubernetes\"\n        ],\n        \"LU4: Kubernetes Configuration and Security (K5, A5)\": [\n            \"Topic 4: Application Environment, Configuration and Security (K5, A5)\",\n            \"Discover and use resources that extend Kubernetes (CRD, Operators)\",\n            \"Understand authentication, authorization and admission control\",\n            \"Understand requests, limits, quotas\",\n            \"Understand ConfigMaps\",\n            \"Define resource requirements\",\n            \"Create & consume Secrets\",\n            \"Understand ServiceAccounts\",\n            \"Understand Application Security (SecurityContexts, Capabilities, etc.)\"\n        ],\n        \"LU5: Application Access and Troubleshooting (K7, A6)\": [\n            \"Topic 5: Services and Networking (K7, A6)\",\n            \"Demonstrate basic understanding of NetworkPolicies\",\n            \"Provide and troubleshoot access to applications via services\",\n            \"Use Ingress rules to expose applications\"\n        ]\n    }\n}\n```", "type": "TextMessage"}], "current_turn": 0, "next_speaker_index": 0}, "collect_output_messages/d97a4206-87a6-4539-820e-115bb0f17fb0": {}, "tsc_agent/d97a4206-87a6-4539-820e-115bb0f17fb0": {"type": "ChatAgentContainerState", "version": "1.0.0", "agent_state": {"type": "AssistantAgentState", "version": "1.0.0", "llm_context": {"messages": [{"content": "\n    1. Parse data from the following JSON file: {'Course_Proposal_Form': {'null': ['Title: Certified Kubernetes Application Developer (CKAD) Training', 'Organization: Tertiary Infotech Pte Ltd', 'Learning Outcomes:', 'LO1: Establish high-level structures and frameworks for Kubernetes solutions using appropriate processes and tools.', 'LO2: Align technical, functional, and service requirements within Kubernetes-based solution architectures.', 'LO3: Coordinate multiple Kubernetes solution components to ensure compatibility and meet design framework goals.', 'LO4: Articulate the value of Kubernetes solutions by addressing coding standards, scalability, and reusability.', 'LO5: Establish monitoring and testing processes to validate Kubernetes architectures against business requirements.', 'Couse Duration: 4 days (32 hrs)', 'Instructional Methods:', 'Classroom (15 hrs),', 'Didactic Questioning', 'Demonstration', 'Practice (15 hrs)', 'Assessment Methods:', 'Written Assessment (1 hr)', 'Practical Performance (1 hr)', 'TSC Mapping:', 'TSC Title: Solution Architecture', 'TSC Code: ICT-DES-5006-1.1', 'TSC Knowledge:', 'K1 Process for refining solution architecture', 'K2 Applications of tools and modelling techniques for creation of solution architecture', 'K3 Technical, functional and service considerations', 'K4 Considerations for multiple aspects of the overall solution including performance, security, latency and other relevant aspect for the solution', 'K5 Standards for coding, scalability, integration and reusability', 'K6 Compatibility among multiple solution architecture components and design activities', \"K7 Techniques to measure a solution's value-add\", 'TSC Abilities:', 'A1 Establish high level structures and frameworks to guide the development of IT solutions incorporating various processes, hardware and software components', 'A2 Determine relevant design tools or modelling techniques required to develop a solution architecture and blueprint', 'A3 Align requirements of various internal and external stakeholders, as well as technical, functional and service requirements within a solution architecture', 'A4 Coordinate multiple solution architecture components and design activities, ensuring consistency and compatibility within a target framework', 'A5 Articulate value added by the solution to the business needs', 'A6 Establish processes to regularly monitor, test and review solution architecture against business requirements', 'Learning Units', 'Topic 1: Application Design and Build (K1, K2, A1, A2)', 'Define, build and modify container images', 'Choose and use the right workload resource (Deployment, DaemonSet, CronJob, etc.)', 'Understand multi-container Pod design patterns (e.g. sidecar, init and others)', 'Utilize persistent and ephemeral volumes', 'Topic 2: Application Deployment (K3, A3)', 'Use Kubernetes primitives to implement common deployment strategies (e.g. blue/green or canary)', 'Understand Deployments and how to perform rolling updates', 'Use the Helm package manager to deploy existing packages', 'Kustomize', 'Topic 3: Application Observability and Maintenance (K4, K6, A4)', 'Understand API deprecations', 'Implement probes and health checks', 'Use built-in CLI tools to monitor Kubernetes applications', 'Utilize container logs', 'Debugging in Kubernetes', 'Topic 4: Application Environment, Configuration and Security (K5, A5)', 'Discover and use resources that extend Kubernetes (CRD, Operators)', 'Understand authentication, authorization and admission control', 'Understand requests, limits, quotas', 'Understand ConfigMaps', 'Define resource requirements', 'Create & consume Secrets', 'Understand ServiceAccounts', 'Understand Application Security (SecurityContexts, Capabilities, etc.)', 'Topic 5: Services and Networking (K7, A6)', 'Demonstrate basic understanding of NetworkPolicies', 'Provide and troubleshoot access to applications via services', 'Use Ingress rules to expose applications']}}\n    2. Fix spelling errors, and missing LUs if any.\n    3. Ensure that the LUs do not have the same name as the Topics.\n    4. Return a full JSON object with all the extracted data according to the schema.\n    ", "source": "user", "type": "UserMessage"}, {"content": "```json\n{\n    \"Course_Proposal_Form\": {\n        \"null\": [\n            \"Title: Certified Kubernetes Application Developer (CKAD) Training\",\n            \"Organization: Tertiary Infotech Pte Ltd\",\n            \"Learning Outcomes:\",\n            \"LO1: Establish high-level structures and frameworks for Kubernetes solutions using appropriate processes and tools.\",\n            \"LO2: Align technical, functional, and service requirements within Kubernetes-based solution architectures.\",\n            \"LO3: Coordinate multiple Kubernetes solution components to ensure compatibility and meet design framework goals.\",\n            \"LO4: Articulate the value of Kubernetes solutions by addressing coding standards, scalability, and reusability.\",\n            \"LO5: Establish monitoring and testing processes to validate Kubernetes architectures against business requirements.\",\n            \"Course Duration: 4 days (32 hrs)\",\n            \"Instructional Methods:\",\n            \"Classroom (15 hrs),\",\n            \"Didactic Questioning\",\n            \"Demonstration\",\n            \"Practical (15 hrs)\",\n            \"Assessment Methods:\",\n            \"Written Assessment (1 hr)\",\n            \"Practical Performance (1 hr)\",\n            \"TSC Mapping:\",\n            \"TSC Title: Solution Architecture\",\n            \"TSC Code: ICT-DES-5006-1.1\",\n            \"TSC Knowledge:\",\n            \"K1: Process for refining solution architecture\",\n            \"K2: Applications of tools and modelling techniques for creation of solution architecture\",\n            \"K3: Technical, functional and service considerations\",\n            \"K4: Considerations for multiple aspects of the overall solution including performance, security, latency and other relevant aspect for the solution\",\n            \"K5: Standards for coding, scalability, integration and reusability\",\n            \"K6: Compatibility among multiple solution architecture components and design activities\",\n            \"K7: Techniques to measure a solution's value-add\",\n            \"TSC Abilities:\",\n            \"A1: Establish high level structures and frameworks to guide the development of IT solutions incorporating various processes, hardware and software components\",\n            \"A2: Determine relevant design tools or modelling techniques required to develop a solution architecture and blueprint\",\n            \"A3: Align requirements of various internal and external stakeholders, as well as technical, functional and service requirements within a solution architecture\",\n            \"A4: Coordinate multiple solution architecture components and design activities, ensuring consistency and compatibility within a target framework\",\n            \"A5: Articulate value added by the solution to the business needs\",\n            \"A6: Establish processes to regularly monitor, test and review solution architecture against business requirements\",\n            \"Learning Units\"\n        ],\n        \"LU1: Container Image Management (K1, K2, A1, A2)\": [\n            \"Topic 1: Application Design and Build (K1, K2, A1, A2)\",\n            \"Define, build and modify container images\",\n            \"Choose and use the right workload resource (Deployment, DaemonSet, CronJob, etc.)\",\n            \"Understand multi-container Pod design patterns (e.g. sidecar, init and others)\",\n            \"Utilize persistent and ephemeral volumes\"\n        ],\n        \"LU2: Deployment Strategy Implementation (K3, A3)\": [\n            \"Topic 2: Application Deployment (K3, A3)\",\n            \"Use Kubernetes primitives to implement common deployment strategies (e.g. blue/green or canary)\",\n            \"Understand Deployments and how to perform rolling updates\",\n            \"Use the Helm package manager to deploy existing packages\",\n            \"Kustomize\"\n        ],\n        \"LU3: Kubernetes Application Monitoring (K4, K6, A4)\": [\n            \"Topic 3: Application Observability and Maintenance (K4, K6, A4)\",\n            \"Understand API deprecations\",\n            \"Implement probes and health checks\",\n            \"Use built-in CLI tools to monitor Kubernetes applications\",\n            \"Utilize container logs\",\n            \"Debugging in Kubernetes\"\n        ],\n        \"LU4: Kubernetes Configuration and Security (K5, A5)\": [\n            \"Topic 4: Application Environment, Configuration and Security (K5, A5)\",\n            \"Discover and use resources that extend Kubernetes (CRD, Operators)\",\n            \"Understand authentication, authorization and admission control\",\n            \"Understand requests, limits, quotas\",\n            \"Understand ConfigMaps\",\n            \"Define resource requirements\",\n            \"Create & consume Secrets\",\n            \"Understand ServiceAccounts\",\n            \"Understand Application Security (SecurityContexts, Capabilities, etc.)\"\n        ],\n        \"LU5: Application Access and Troubleshooting (K7, A6)\": [\n            \"Topic 5: Services and Networking (K7, A6)\",\n            \"Demonstrate basic understanding of NetworkPolicies\",\n            \"Provide and troubleshoot access to applications via services\",\n            \"Use Ingress rules to expose applications\"\n        ]\n    }\n}\n```", "source": "tsc_agent", "type": "AssistantMessage"}]}}, "message_buffer": []}}, "team_id": "d97a4206-87a6-4539-820e-115bb0f17fb0"}