{"type": "TeamState", "version": "1.0.0", "agent_states": {"group_chat_manager/ae6e9e22-f0af-4d52-8111-64838e16c6e3": {"type": "RoundRobinManagerState", "version": "1.0.0", "message_thread": [{"source": "user", "models_usage": null, "content": "\n    1. Parse data from the following JSON file: {'Course_Proposal_Form': {'null': ['Title: Github Foundations Certification Training', 'Organization:  Tertiary Infotech Pte Ltd', 'Learning Outcomes:', 'LO1: Analyze Github components and coordinate release scheduling with collaborators to align processes.', 'LO2: Select appropriate Git scripts for integrating and deploying software products .', 'LO3: Configure software products and deploy releases using Git configuration tests.', 'LO4: Diagnose issues identified during Github configuration testing by interpreting configuration test results.', 'LO5: Identify potential improvements to the software configuration, deployment processes, and code elements.', 'LO6: Implement modifications to software products and processes for improved functionality.', 'Couse Duration: 2 days (16 hrs)', 'Instructional Methods:', 'Classroom (7hrs),', 'Didactic Questioning', 'Demonstration', 'Practice (7 hrs)', 'Assessment Methods:', 'Written Assessment (1 hr)', 'Practical Performance (1 hr)', 'TSC Mapping:', 'TSC Title: Software Configuration', 'TSC Code: ICT-DIT-3014-1.1', 'TSC Knowledge:', 'K1 Types and usage of scripts and tools for integrating and deploying software products', 'K2 Software configuration procedures', 'K3 Configuration tests and their purposes', 'K4 Interpretation of configuration test results', 'K5 Elements of the software configuration and deployment process', 'TSC Abilities:', 'A1 Analyse release components', 'A2 Coordinate with relevant stakeholders on release scheduling to align release processes and procedures', 'A3 Select appropriate scripts and tools for integrating and deploying software products', 'A4 Configure software products to integrate and deploy software releases to various platforms', 'A5 Execute configuration tests on platform specific versions of software products in line with testing procedures', 'A6 Diagnose issues surfaced from configuration testing', 'A7 Identify potential improvements and modifications to the software configuration and deployment process or the software code', 'A8 Implement modifications to platform-specific software products and processes', 'Learning Units'], 'LU1: Introduction to Git and GitHub (A1, A2)': ['Topic 1: Introduction to Git and GitHub (A1, A2)', 'What is vesion control', 'Basic Git commands', 'What is GitHub?', 'Components of the GitHub flow', 'GitHub is a collaborative platform', 'GitHub platform management'], 'LU2: Working with GitHub Repository (K1, A3)': ['Topic 2:  Working with GitHub Repository (K1, A3)', 'Repository management', 'Create a new GitHub Repository', 'Clone a repository', 'Create a new branch', 'Add files to a repository', 'Manage repository changes by using pull requests on GitHub', 'View repository insights'], 'LU3: Collaboration Features (K2, K3, A4, A5)': ['Topic 3: Collaboration Features (K2, K3, A4, A5)', 'Managing issues and discussions', 'Forking and pull requests', 'GitHub pages', 'Markdown Features', 'Link a PR to an Issue', 'Identify how to assign Issues.', 'Code reviews'], 'LU4: Modern Development  (K4, A6)': ['Topic 4: Modern Development  (K4, A6)', 'GitHub Actions', 'GitHub Copilot', 'GitHub Codespaces'], 'LU5: GitHub Project (K5, A7)': ['Topic 5: GitHub Project (K5, A7)', 'Projects versus Projects Classic', 'How to create a project', 'How to organize your project', 'How to organize and automate your project', 'Insight and automation with projects'], 'LU6: Privacy, Security and Administration (A8)': ['Topic 6: Privacy, Security and Administration (A8)', 'Introduction to GitHub administration', 'Authenticate and authorize user identities on GitHub', 'Dependency management', 'Code scanning', 'Secret scanning', 'How to maintain a secure GitHub repository', 'Automated security', 'InnerSouce']}}\n    2. Fix spelling errors, and missing LUs if any.\n    3. Ensure that the LUs do not have the same name as the Topics.\n    4. Return a full JSON object with all the extracted data according to the schema.\n    ", "type": "TextMessage"}, {"source": "tsc_agent", "models_usage": {"prompt_tokens": 2531, "completion_tokens": 1027}, "content": "```json\n{\n    \"Course_Proposal_Form\": {\n        \"null\": [\n            \"Title: Github Foundations Certification Training\",\n            \"Organization: Tertiary Infotech Pte Ltd\",\n            \"Learning Outcomes:\",\n            \"LO1: Analyze Github components and coordinate release scheduling with collaborators to align processes.\",\n            \"LO2: Select appropriate Git scripts for integrating and deploying software products.\",\n            \"LO3: Configure software products and deploy releases using Git configuration tests.\",\n            \"LO4: Diagnose issues identified during Github configuration testing by interpreting configuration test results.\",\n            \"LO5: Identify potential improvements to the software configuration, deployment processes, and code elements.\",\n            \"LO6: Implement modifications to software products and processes for improved functionality.\",\n            \"Course Duration: 2 days (16 hrs)\",\n            \"Instructional Methods:\",\n            \"Classroom (7hrs),\",\n            \"Didactic Questioning\",\n            \"Demonstration\",\n            \"Practical (7 hrs)\",\n            \"Assessment Methods:\",\n            \"Written Assessment (1 hr)\",\n            \"Practical Performance (1 hr)\",\n            \"TSC Mapping:\",\n            \"TSC Title: Software Configuration\",\n            \"TSC Code: ICT-DIT-3014-1.1\",\n            \"TSC Knowledge:\",\n            \"K1: Types and usage of scripts and tools for integrating and deploying software products\",\n            \"K2: Software configuration procedures\",\n            \"K3: Configuration tests and their purposes\",\n            \"K4: Interpretation of configuration test results\",\n            \"K5: Elements of the software configuration and deployment process\",\n            \"TSC Abilities:\",\n            \"A1: Analyse release components\",\n            \"A2: Coordinate with relevant stakeholders on release scheduling to align release processes and procedures\",\n            \"A3: Select appropriate scripts and tools for integrating and deploying software products\",\n            \"A4: Configure software products to integrate and deploy software releases to various platforms\",\n            \"A5: Execute configuration tests on platform specific versions of software products in line with testing procedures\",\n            \"A6: Diagnose issues surfaced from configuration testing\",\n            \"A7: Identify potential improvements and modifications to the software configuration and deployment process or the software code\",\n            \"A8: Implement modifications to platform-specific software products and processes\",\n            \"Learning Units\"\n        ],\n        \"LU1: Git and GitHub Fundamentals (A1, A2)\": [\n            \"Topic 1: Introduction to Git and GitHub (A1, A2)\",\n            \"What is version control\",\n            \"Basic Git commands\",\n            \"What is GitHub?\",\n            \"Components of the GitHub flow\",\n            \"GitHub is a collaborative platform\",\n            \"GitHub platform management\"\n        ],\n        \"LU2: GitHub Repository Management (K1, A3)\": [\n            \"Topic 2: Working with GitHub Repository (K1, A3)\",\n            \"Repository management\",\n            \"Create a new GitHub Repository\",\n            \"Clone a repository\",\n            \"Create a new branch\",\n            \"Add files to a repository\",\n            \"Manage repository changes by using pull requests on GitHub\",\n            \"View repository insights\"\n        ],\n        \"LU3: Collaborative Workflows on GitHub (K2, K3, A4, A5)\": [\n            \"Topic 3: Collaboration Features (K2, K3, A4, A5)\",\n            \"Managing issues and discussions\",\n            \"Forking and pull requests\",\n            \"GitHub pages\",\n            \"Markdown Features\",\n            \"Link a PR to an Issue\",\n            \"Identify how to assign Issues.\",\n            \"Code reviews\"\n        ],\n        \"LU4: Modern GitHub Development Practices (K4, A6)\": [\n            \"Topic 4: Modern Development (K4, A6)\",\n            \"GitHub Actions\",\n            \"GitHub Copilot\",\n            \"GitHub Codespaces\"\n        ],\n        \"LU5: GitHub Project Automation (K5, A7)\": [\n            \"Topic 5: GitHub Project (K5, A7)\",\n            \"Projects versus Projects Classic\",\n            \"How to create a project\",\n            \"How to organize your project\",\n            \"How to organize and automate your project\",\n            \"Insight and automation with projects\"\n        ],\n        \"LU6: GitHub Security and Administration (A8)\": [\n            \"Topic 6: Privacy, Security and Administration (A8)\",\n            \"Introduction to GitHub administration\",\n            \"Authenticate and authorize user identities on GitHub\",\n            \"Dependency management\",\n            \"Code scanning\",\n            \"Secret scanning\",\n            \"How to maintain a secure GitHub repository\",\n            \"Automated security\",\n            \"InnerSouce\"\n        ]\n    }\n}\n```", "type": "TextMessage"}], "current_turn": 0, "next_speaker_index": 0}, "collect_output_messages/ae6e9e22-f0af-4d52-8111-64838e16c6e3": {}, "tsc_agent/ae6e9e22-f0af-4d52-8111-64838e16c6e3": {"type": "ChatAgentContainerState", "version": "1.0.0", "agent_state": {"type": "AssistantAgentState", "version": "1.0.0", "llm_context": {"messages": [{"content": "\n    1. Parse data from the following JSON file: {'Course_Proposal_Form': {'null': ['Title: Github Foundations Certification Training', 'Organization:  Tertiary Infotech Pte Ltd', 'Learning Outcomes:', 'LO1: Analyze Github components and coordinate release scheduling with collaborators to align processes.', 'LO2: Select appropriate Git scripts for integrating and deploying software products .', 'LO3: Configure software products and deploy releases using Git configuration tests.', 'LO4: Diagnose issues identified during Github configuration testing by interpreting configuration test results.', 'LO5: Identify potential improvements to the software configuration, deployment processes, and code elements.', 'LO6: Implement modifications to software products and processes for improved functionality.', 'Couse Duration: 2 days (16 hrs)', 'Instructional Methods:', 'Classroom (7hrs),', 'Didactic Questioning', 'Demonstration', 'Practice (7 hrs)', 'Assessment Methods:', 'Written Assessment (1 hr)', 'Practical Performance (1 hr)', 'TSC Mapping:', 'TSC Title: Software Configuration', 'TSC Code: ICT-DIT-3014-1.1', 'TSC Knowledge:', 'K1 Types and usage of scripts and tools for integrating and deploying software products', 'K2 Software configuration procedures', 'K3 Configuration tests and their purposes', 'K4 Interpretation of configuration test results', 'K5 Elements of the software configuration and deployment process', 'TSC Abilities:', 'A1 Analyse release components', 'A2 Coordinate with relevant stakeholders on release scheduling to align release processes and procedures', 'A3 Select appropriate scripts and tools for integrating and deploying software products', 'A4 Configure software products to integrate and deploy software releases to various platforms', 'A5 Execute configuration tests on platform specific versions of software products in line with testing procedures', 'A6 Diagnose issues surfaced from configuration testing', 'A7 Identify potential improvements and modifications to the software configuration and deployment process or the software code', 'A8 Implement modifications to platform-specific software products and processes', 'Learning Units'], 'LU1: Introduction to Git and GitHub (A1, A2)': ['Topic 1: Introduction to Git and GitHub (A1, A2)', 'What is vesion control', 'Basic Git commands', 'What is GitHub?', 'Components of the GitHub flow', 'GitHub is a collaborative platform', 'GitHub platform management'], 'LU2: Working with GitHub Repository (K1, A3)': ['Topic 2:  Working with GitHub Repository (K1, A3)', 'Repository management', 'Create a new GitHub Repository', 'Clone a repository', 'Create a new branch', 'Add files to a repository', 'Manage repository changes by using pull requests on GitHub', 'View repository insights'], 'LU3: Collaboration Features (K2, K3, A4, A5)': ['Topic 3: Collaboration Features (K2, K3, A4, A5)', 'Managing issues and discussions', 'Forking and pull requests', 'GitHub pages', 'Markdown Features', 'Link a PR to an Issue', 'Identify how to assign Issues.', 'Code reviews'], 'LU4: Modern Development  (K4, A6)': ['Topic 4: Modern Development  (K4, A6)', 'GitHub Actions', 'GitHub Copilot', 'GitHub Codespaces'], 'LU5: GitHub Project (K5, A7)': ['Topic 5: GitHub Project (K5, A7)', 'Projects versus Projects Classic', 'How to create a project', 'How to organize your project', 'How to organize and automate your project', 'Insight and automation with projects'], 'LU6: Privacy, Security and Administration (A8)': ['Topic 6: Privacy, Security and Administration (A8)', 'Introduction to GitHub administration', 'Authenticate and authorize user identities on GitHub', 'Dependency management', 'Code scanning', 'Secret scanning', 'How to maintain a secure GitHub repository', 'Automated security', 'InnerSouce']}}\n    2. Fix spelling errors, and missing LUs if any.\n    3. Ensure that the LUs do not have the same name as the Topics.\n    4. Return a full JSON object with all the extracted data according to the schema.\n    ", "source": "user", "type": "UserMessage"}, {"content": "```json\n{\n    \"Course_Proposal_Form\": {\n        \"null\": [\n            \"Title: Github Foundations Certification Training\",\n            \"Organization: Tertiary Infotech Pte Ltd\",\n            \"Learning Outcomes:\",\n            \"LO1: Analyze Github components and coordinate release scheduling with collaborators to align processes.\",\n            \"LO2: Select appropriate Git scripts for integrating and deploying software products.\",\n            \"LO3: Configure software products and deploy releases using Git configuration tests.\",\n            \"LO4: Diagnose issues identified during Github configuration testing by interpreting configuration test results.\",\n            \"LO5: Identify potential improvements to the software configuration, deployment processes, and code elements.\",\n            \"LO6: Implement modifications to software products and processes for improved functionality.\",\n            \"Course Duration: 2 days (16 hrs)\",\n            \"Instructional Methods:\",\n            \"Classroom (7hrs),\",\n            \"Didactic Questioning\",\n            \"Demonstration\",\n            \"Practical (7 hrs)\",\n            \"Assessment Methods:\",\n            \"Written Assessment (1 hr)\",\n            \"Practical Performance (1 hr)\",\n            \"TSC Mapping:\",\n            \"TSC Title: Software Configuration\",\n            \"TSC Code: ICT-DIT-3014-1.1\",\n            \"TSC Knowledge:\",\n            \"K1: Types and usage of scripts and tools for integrating and deploying software products\",\n            \"K2: Software configuration procedures\",\n            \"K3: Configuration tests and their purposes\",\n            \"K4: Interpretation of configuration test results\",\n            \"K5: Elements of the software configuration and deployment process\",\n            \"TSC Abilities:\",\n            \"A1: Analyse release components\",\n            \"A2: Coordinate with relevant stakeholders on release scheduling to align release processes and procedures\",\n            \"A3: Select appropriate scripts and tools for integrating and deploying software products\",\n            \"A4: Configure software products to integrate and deploy software releases to various platforms\",\n            \"A5: Execute configuration tests on platform specific versions of software products in line with testing procedures\",\n            \"A6: Diagnose issues surfaced from configuration testing\",\n            \"A7: Identify potential improvements and modifications to the software configuration and deployment process or the software code\",\n            \"A8: Implement modifications to platform-specific software products and processes\",\n            \"Learning Units\"\n        ],\n        \"LU1: Git and GitHub Fundamentals (A1, A2)\": [\n            \"Topic 1: Introduction to Git and GitHub (A1, A2)\",\n            \"What is version control\",\n            \"Basic Git commands\",\n            \"What is GitHub?\",\n            \"Components of the GitHub flow\",\n            \"GitHub is a collaborative platform\",\n            \"GitHub platform management\"\n        ],\n        \"LU2: GitHub Repository Management (K1, A3)\": [\n            \"Topic 2: Working with GitHub Repository (K1, A3)\",\n            \"Repository management\",\n            \"Create a new GitHub Repository\",\n            \"Clone a repository\",\n            \"Create a new branch\",\n            \"Add files to a repository\",\n            \"Manage repository changes by using pull requests on GitHub\",\n            \"View repository insights\"\n        ],\n        \"LU3: Collaborative Workflows on GitHub (K2, K3, A4, A5)\": [\n            \"Topic 3: Collaboration Features (K2, K3, A4, A5)\",\n            \"Managing issues and discussions\",\n            \"Forking and pull requests\",\n            \"GitHub pages\",\n            \"Markdown Features\",\n            \"Link a PR to an Issue\",\n            \"Identify how to assign Issues.\",\n            \"Code reviews\"\n        ],\n        \"LU4: Modern GitHub Development Practices (K4, A6)\": [\n            \"Topic 4: Modern Development (K4, A6)\",\n            \"GitHub Actions\",\n            \"GitHub Copilot\",\n            \"GitHub Codespaces\"\n        ],\n        \"LU5: GitHub Project Automation (K5, A7)\": [\n            \"Topic 5: GitHub Project (K5, A7)\",\n            \"Projects versus Projects Classic\",\n            \"How to create a project\",\n            \"How to organize your project\",\n            \"How to organize and automate your project\",\n            \"Insight and automation with projects\"\n        ],\n        \"LU6: GitHub Security and Administration (A8)\": [\n            \"Topic 6: Privacy, Security and Administration (A8)\",\n            \"Introduction to GitHub administration\",\n            \"Authenticate and authorize user identities on GitHub\",\n            \"Dependency management\",\n            \"Code scanning\",\n            \"Secret scanning\",\n            \"How to maintain a secure GitHub repository\",\n            \"Automated security\",\n            \"InnerSouce\"\n        ]\n    }\n}\n```", "source": "tsc_agent", "type": "AssistantMessage"}]}}, "message_buffer": []}}, "team_id": "ae6e9e22-f0af-4d52-8111-64838e16c6e3"}